muqi/__init__.py
muqi/greet.py
muqi-0.1.0.dist-info/LICENSE
muqi-0.1.0.dist-info/METADATA
muqi-0.1.0.dist-info/WHEEL
muqi-0.1.0.dist-info/top_level.txt
muqi-0.1.0.dist-info/RECORD
